muler/__init__.py
muler/echelle.py
muler/hpf.py
muler/igrins.py
muler/mage.py
muler/nirspec.py
muler/utilities.py
muler/templates/HPF_blaze_templates.csv
muler/templates/HPF_sci_to_sky_ratio_beta.csv
muler/templates/PHOENIX_10kK_hpf_template.csv
muler/templates/__init__.py
muler/templates/color_grid_full.csv
muler/templates/psg_trn_r100000_1.4_2.5_um.txt
muler/templates/telfit_HPFtemplate_temp286_hum050.csv
muler-0.5.6.dist-info/licenses/LICENSE
muler-0.5.6.dist-info/METADATA
muler-0.5.6.dist-info/WHEEL
muler-0.5.6.dist-info/top_level.txt
muler-0.5.6.dist-info/RECORD
