Metadata-Version: 2.4
Name: muler
Version: 0.5.6
Summary: A Python package for working with data from various echelle spectrographs
Home-page: https://github.com/OttoStruve/muler
Author: gully
Author-email: igully@gmail.com
Classifier: Programming Language :: Python :: 3
Classifier: License :: OSI Approved :: MIT License
Classifier: Operating System :: OS Independent
Requires-Python: >=3.8
License-File: LICENSE
Requires-Dist: numpy
Requires-Dist: scipy
Requires-Dist: astropy>=5.2
Requires-Dist: specutils>=2.1
Requires-Dist: pandas
Requires-Dist: importlib_resources
Requires-Dist: matplotlib
Provides-Extra: extra
Requires-Dist: celerite2; extra == "extra"
Requires-Dist: h5py; extra == "extra"
Requires-Dist: black; extra == "extra"
Dynamic: author
Dynamic: author-email
Dynamic: classifier
Dynamic: description
Dynamic: description-content-type
Dynamic: home-page
Dynamic: license-file
Dynamic: provides-extra
Dynamic: requires-dist
Dynamic: requires-python
Dynamic: summary
